bfg/__init__.py
bfg/aggregator.py
bfg/ammo.py
bfg/cli.py
bfg/config.py
bfg/loadtest.py
bfg/module_exceptions.py
bfg/schedule.py
bfg/util.py
bfg/worker.py
bfg/config/example.toml
bfg-0.0.2.dist-info/DESCRIPTION.rst
bfg-0.0.2.dist-info/entry_points.txt
bfg-0.0.2.dist-info/METADATA
bfg-0.0.2.dist-info/metadata.json
bfg-0.0.2.dist-info/RECORD
bfg-0.0.2.dist-info/top_level.txt
bfg-0.0.2.dist-info/WHEEL
