Metadata-Version: 2.0
Name: bfg
Version: 0.0.2
Summary: a load generation tool and framework
Home-page: https://github.com/direvius/bfg
Author: Alexey Lavrenuke (load testing)
Author-email: direvius@gmail.com
License: MIT
Platform: UNKNOWN
Classifier: Development Status :: 1 - Planning
Classifier: Environment :: Console
Classifier: Environment :: Web Environment
Classifier: Intended Audience :: Developers
Classifier: Intended Audience :: System Administrators
Classifier: License :: OSI Approved :: MIT License
Classifier: Operating System :: POSIX
Classifier: Topic :: Software Development :: Quality Assurance
Classifier: Topic :: Software Development :: Testing
Classifier: Topic :: Software Development :: Testing :: Traffic Generation
Classifier: Topic :: System :: Benchmark
Classifier: Programming Language :: Python :: 3
Requires-Dist: hyper
Requires-Dist: numpy
Requires-Dist: pandas
Requires-Dist: PyYAML
Requires-Dist: pytoml
